{
    "0": {
        "No Spell": "No Spell"
    },
    "1": {
        "No Spell": "No Spell"
    },
    "2": {
        "Fire" : {
            "name": "Fire",
            "description": "A fireball that deals 1d6 damage to a single target.",
            "damage": "1d6",
            "additionals" : ["Attack Damage increase"]
        },
        "Heal" : {
            "name": "Heal",
            "description": "Heals a single target for 1d6 health.",
            "heal": "1d6",
            "additionals" : ["Heal increase"]
        }
    },
    "3": {
        "No Spell": "No Spell"
    },
    "4": {
        "No Spell": "No Spell"
    },
    "5": {
        "No Spell": "No Spell"
    },
    "6": {
        "No Spell": "No Spell"
    },
    "7": {
        "No Spell": "No Spell"
    },
    "8": {
        "No Spell": "No Spell"
    },
    "9": {
        "No Spell": "No Spell"
    }
}